agenthub/README.md
agenthub/__init__.py
agenthub/browsing_agent/README.md
agenthub/browsing_agent/__init__.py
agenthub/browsing_agent/browsing_agent.py
agenthub/browsing_agent/prompt.py
agenthub/browsing_agent/response_parser.py
agenthub/browsing_agent/utils.py
agenthub/codeact_agent/README.md
agenthub/codeact_agent/__init__.py
agenthub/codeact_agent/action_parser.py
agenthub/codeact_agent/codeact_agent.py
agenthub/codeact_agent/micro/github.md
agenthub/codeact_agent/system_prompt.j2
agenthub/codeact_agent/user_prompt.j2
agenthub/codeact_swe_agent/README.md
agenthub/codeact_swe_agent/__init__.py
agenthub/codeact_swe_agent/action_parser.py
agenthub/codeact_swe_agent/codeact_swe_agent.py
agenthub/codeact_swe_agent/prompt.py
agenthub/codeact_swe_agent/response_parser.py
agenthub/delegator_agent/__init__.py
agenthub/delegator_agent/agent.py
agenthub/dummy_agent/__init__.py
agenthub/dummy_agent/agent.py
agenthub/micro/README.md
agenthub/micro/_instructions/actions/browse.md
agenthub/micro/_instructions/actions/delegate.md
agenthub/micro/_instructions/actions/finish.md
agenthub/micro/_instructions/actions/kill.md
agenthub/micro/_instructions/actions/message.md
agenthub/micro/_instructions/actions/read.md
agenthub/micro/_instructions/actions/reject.md
agenthub/micro/_instructions/actions/run.md
agenthub/micro/_instructions/actions/write.md
agenthub/micro/_instructions/format/action.md
agenthub/micro/_instructions/history_truncated.md
agenthub/micro/agent.py
agenthub/micro/coder/agent.yaml
agenthub/micro/coder/prompt.md
agenthub/micro/commit_writer/README.md
agenthub/micro/commit_writer/agent.yaml
agenthub/micro/commit_writer/prompt.md
agenthub/micro/instructions.py
agenthub/micro/manager/agent.yaml
agenthub/micro/manager/prompt.md
agenthub/micro/math_agent/agent.yaml
agenthub/micro/math_agent/prompt.md
agenthub/micro/postgres_agent/agent.yaml
agenthub/micro/postgres_agent/prompt.md
agenthub/micro/registry.py
agenthub/micro/repo_explorer/agent.yaml
openhands_ai_test-0.9.6.dist-info/LICENSE
openhands_ai_test-0.9.6.dist-info/METADATA
openhands_ai_test-0.9.6.dist-info/WHEEL
openhands_ai_test-0.9.6.dist-info/entry_points.txt
openhands_ai_test-0.9.6.dist-info/RECORD
